eros_cli/__init__.py
eros_cli/__main__.py
eros_cli/entrypoint.py
eros_cli/app/app_cli.py
eros_cli/app/app_dump.py
eros_cli/app/app_log.py
eros_cli/app/app_machine_cli.py
eros_cli/app/app_perf.py
eros_cli/app/app_zmq.py
eros_cli/app/decorators.py
eros_cli/app/utils/eros_terminal.py
eros_cli/app/utils/transport_status_log.py
eros_cli/transport/drv_tcp.py
eros_cli/transport/drv_uart.py
eros_cli/transport/drv_udp.py
eros_cli/transport/drv_zmq.py
eros_cli-1.0.4.dist-info/METADATA
eros_cli-1.0.4.dist-info/WHEEL
eros_cli-1.0.4.dist-info/entry_points.txt
eros_cli-1.0.4.dist-info/licenses/LICENCE
eros_cli-1.0.4.dist-info/RECORD
