Metadata-Version: 2.1
Name: eros-cli
Version: 1.0.4
Summary: A package to view EROS logs
Author-email: Floris Vernieuwe <floris@vernieuwe.eu>
License-File: LICENCE
Classifier: Programming Language :: Python :: 3
Requires-Python: >=3.10
Requires-Dist: blessed
Requires-Dist: click==8.1.3
Requires-Dist: eros-core==1.0.6
Requires-Dist: rich==13.4.2
Requires-Dist: si-prefix==1.2.2
